rosmap/__init__.py
rosmap/__init__.pyc
rosmap/analyze.py
rosmap/__pycache__/__init__.cpython-35.pyc
rosmap/__pycache__/analyze.cpython-35.pyc
rosmap/api_bindings/__init__.py
rosmap/api_bindings/bitbucket_api_bindings.py
rosmap/api_bindings/github_api_bindings.py
rosmap/api_bindings/__pycache__/__init__.cpython-35.pyc
rosmap/api_bindings/__pycache__/bitbucket_api_bindings.cpython-35.pyc
rosmap/api_bindings/__pycache__/github_api_bindings.cpython-35.pyc
rosmap/config/__init__.py
rosmap/config/config.json
rosmap/config/config.json_backup
rosmap/file_analyzers/__init__.py
rosmap/file_analyzers/cpp_file_analyzer.py
rosmap/file_analyzers/existence_file_analyzer.py
rosmap/file_analyzers/i_file_analyzer.py
rosmap/file_analyzers/__pycache__/__init__.cpython-35.pyc
rosmap/file_analyzers/__pycache__/cpp_file_analyzer.cpython-35.pyc
rosmap/file_analyzers/__pycache__/existence_file_analyzer.cpython-35.pyc
rosmap/file_analyzers/__pycache__/i_file_analyzer.cpython-35.pyc
rosmap/loaders/__init__.py
rosmap/loaders/module_loader.py
rosmap/loaders/__pycache__/__init__.cpython-35.pyc
rosmap/loaders/__pycache__/module_loader.cpython-35.pyc
rosmap/package_analyzers/manifest_xml_analyzer.py
rosmap/package_analyzers/package_analyzer.py
rosmap/package_analyzers/package_xml_analyzer.py
rosmap/package_analyzers/__pycache__/manifest_xml_analyzer.cpython-35.pyc
rosmap/package_analyzers/__pycache__/package_analyzer.cpython-35.pyc
rosmap/package_analyzers/__pycache__/package_xml_analyzer.cpython-35.pyc
rosmap/repository_analyzers/__init__.py
rosmap/repository_analyzers/__pycache__/__init__.cpython-35.pyc
rosmap/repository_analyzers/offline/__init__.py
rosmap/repository_analyzers/offline/abstract_repository_analyzer.py
rosmap/repository_analyzers/offline/git_repository_analyzer.py
rosmap/repository_analyzers/offline/i_repository_analyzer.py
rosmap/repository_analyzers/offline/mercurial_repository_analyzer.py
rosmap/repository_analyzers/offline/subversion_repository_analyzer.py
rosmap-0.2.dist-info/LICENSE.txt
rosmap-0.2.dist-info/METADATA
rosmap-0.2.dist-info/WHEEL
rosmap-0.2.dist-info/top_level.txt
rosmap-0.2.dist-info/RECORD
